hfa_oauth_sdk/__init__.py
hfa_oauth_sdk/auth.py
hfa_oauth_sdk/test_redirect.py
hfa_oauth_sdk/test_token.py
hfa_oauth_sdk/utility.py
hypers_oauth2-0.1.dist-info/DESCRIPTION.rst
hypers_oauth2-0.1.dist-info/METADATA
hypers_oauth2-0.1.dist-info/RECORD
hypers_oauth2-0.1.dist-info/WHEEL
hypers_oauth2-0.1.dist-info/metadata.json
hypers_oauth2-0.1.dist-info/top_level.txt
